{
    "aboutMe": {
        "title": {
            "default": "Hello! I'm Gabriel",
            "bold": "Cix"
        },
        "description": "junior full stack developer",
        "contact": {
            "link": "/contacts",
            "label": "Talk to me!"
        },
        "techs": [
            {
                "tech": "typescript",
                "color": "#000000",
                "bgcolor": "#007ACC"
            },
            {
                "tech": "next.js",
                "color": "#FFFFFF",
                "bgcolor": "#000000"
            },
            {
                "tech": "node.js",
                "color": "#000000",
                "bgcolor": "#8CC84B"
            },
            {
                "tech": "python",
                "color": "#FCC624",
                "bgcolor": "#306998"
            },
            {
                "tech": "wordpress",
                "color": "#FFFFFF",
                "bgcolor": "#21759B"
            },
            {
                "tech": "linux",
                "color": "#000000",
                "bgcolor": "#FCC624"
            },
            {
                "tech": "insomnia",
                "color": "#FFFFFF",
                "bgcolor": "#4C8BF5"
            },
            {
                "tech": "bootstrap",
                "color": "#FFFFFF",
                "bgcolor": "#563D7C"
            },
            {
                "tech": "tailwind",
                "color": "#FFFFFF",
                "bgcolor": "#38B2AC"
            },
            {
                "tech": "git",
                "color": "#FFFFFF",
                "bgcolor": "#F05032"
            },
            {
                "tech": "github",
                "color": "#FFFFFF",
                "bgcolor": "#181717"
            },
            {
                "tech": "vscode",
                "color": "#FFFFFF",
                "bgcolor": "#007ACC"
            }
        ],
        "pfp": {
            "image": {
                "url": "https://avatars.githubusercontent.com/u/102544926?v=4",
                "alt": "Cix's Profile Picture"
            },
            "experience": {
                "default": "years of experience",
                "bold": "2+"
            }
        }
    },
    "projects": [
        {
            "slug": "linktree",
            "name": "LinkTree",
            "external": "https://ttvcixayah.vercel.app",
            "image": {
                "url": "https://img001.prntscr.com/file/img001/4Jz3M18BQlW0liHJ8ALBPw.png",
                "alt": "A link tree, the main icon is a cat biting a Gengar plush"
            }
        },
        {
            "slug": "pokedex",
            "name": "Pokédex",
            "external": "https://cixayah.github.io/pokedex/",
            "image": {
                "url": "https://img001.prntscr.com/file/img001/xurDZK4YQ1aqKm5UuIOFzA.png",
                "alt": "Pokédex with Gengar"
            }
        },
        {
            "slug": "todo-list",
            "name": "TODO List",
            "external": "https://necessary-silk-teal.glitch.me/",
            "image": {
                "url": "https://lh3.googleusercontent.com/pw/AP1GczPGMe-3JPrMnw84I_tpqMf7myMPJTH4ejvFgrAYwh8xMxsosuPvlA56dZWTZrSfC-jroin8eagW4li56_60H6cTf0H1sg6X38GqBoHglDgfdlXRCH8sOieo3Ji_m7sj6TqgmwTxGWIEV5tyg0y8XmUX=w400-h434-s-no-gm?authuser=0",
                "alt": "TODO List Screenshot"
            }
        },
        {
            "slug": "auth-jwt",
            "name": "Auth JWT",
            "external": "https://cixayah.github.io/html-jwt/",
            "image": {
                "url": "https://lh3.googleusercontent.com/pw/AP1GczPUPXlYGFsQu4HYrtA3v0lKY53NlzkGB7LIo76itm5XGncoryl6JFPtu7HhRZQBCZ0VnVpd8S6ZrrnaVqlhNo54pQJg_Jh-QvRFEYD4sGz78C0dWGZIwfZR7HT_VFC-MAjF2LXmCnzqPgyt9h2ZubjN=w418-h406-s-no-gm?authuser=0",
                "alt": "A Login with a white background and a form with email and password fields"
            }
        },
        {
            "slug": "hungar-bot-discord",
            "name": "Hungar - Discord Bot",
            "external": "https://github.com/Cixayah/Hungar",
            "image": {
                "url": "https://lh3.googleusercontent.com/pw/AP1GczN9ztE-DjykOS9quWvPCPgDlJHjxB8vtsmEzHGJWwN41OBUrQM-l64mVyKk_CguDZj-cPbk7e33MHS4uHNGjg1PyZHuZT8SHIdMoK35EVbBIfmQYvC3bfRMvVqh2H6tstUzTq-62vwXJ6DK-gvsbZgG=w362-h343-s-no-gm?authuser=0",
                "alt": "Hungar bot photo, with Gengar in black and without background"
            }
        },
        {
            "slug": "my-expenses-flash",
            "name": "My Expenses - Flask",
            "external": "https://meus-gastos-two.vercel.app/",
            "image": {
                "url": "https://lh3.googleusercontent.com/pw/AP1GczN4IpdHij9AGb86fT4kAeOcSMpQ7rFf87a3jjAl5C6GT7ctabo8t5hjabry3Peq7KSkOSzlyqt-m4eG41-2BZW1fTyZx3Vim_LKXIVAspoWveJfImVvbzRNHE1l_xcvUickZMKg0LaTegjN-Hq0OpfJ=w626-h590-s-no-gm?authuser=0",
                "alt": "Interface with colorful theme, with description, value, and email fields"
            }
        },
        {
            "slug": "csharp-project",
            "name": "Crud in C# Windows Forms",
            "external": "https://github.com/Cixayah/cs-sales-control",
            "image": {
                "url": "https://lh3.googleusercontent.com/pw/AP1GczPPG0D4pfGLCarqIMOLyCYM1AXW5FBJ-T9ALdJ0et9ty7E94IBYFV3LfqONR5DuSH57pcIMivDPHKW6abyfTEHOJQEb_nVJzpz74EAE6eIYM9JABrUFr-Tc6y2Eeu-WOxde8zfhoGFt9ls201G8Mq4B=w316-h320-s-no-gm?authuser=0",
                "alt": "Interface application, with a form with name, email, and phone fields"
            }
        },
        {
            "slug": "gym-cix",
            "name": "Gym Cix",
            "external": "https://gym-cix.vercel.app",
            "image": {
                "url": "hhttps://lh3.googleusercontent.com/pw/AP1GczPuYznPdgAggDAliUUcn00zaFNC_zEU5jqOz-UpV7RHtG0TPgdosOUTmFw7zJFztY-EEmtIO7dvaKBq_cyPenwN35pWq-GHyXDHvONvt1L8mOWe8QDK4aa4Z5GYfWu2z8cVb8kth5sPbj-LUxt1WU7S=w500-h500-s-no-gm?authuser=0",
                "alt": "A website developed for a fictitious gym"
            }
        }
    ]
}